Metadata-Version: 2.2
Name: xnlbd
Version: 0.0.3
Summary: Nonlinear beam dynamics tools for Xsuite
Author-email: "Dora E. Veres (github.com/deveres99)" <dora.erzsebet.veres@cern.ch>
License:                                  Apache License
Project-URL: Homepage, https://github.com/deveres99/xnlbd
Requires-Python: >=3.9
License-File: LICENSE
Requires-Dist: xobjects>=0.4.1
Requires-Dist: xdeps>=0.6.0
Requires-Dist: xpart>=0.18.2
Requires-Dist: xtrack>=0.61.0
Requires-Dist: xcoll>=0.5.8
Requires-Dist: numpy
Requires-Dist: numba
Requires-Dist: pandas
Requires-Dist: scipy
Requires-Dist: sympy
Requires-Dist: matplotlib
Requires-Dist: h5py
Provides-Extra: dev
Requires-Dist: pytest; extra == "dev"
Requires-Dist: black; extra == "dev"
Requires-Dist: mypy; extra == "dev"
Requires-Dist: isort; extra == "dev"
Requires-Dist: pandas-stubs; extra == "dev"
Requires-Dist: types-tqdm; extra == "dev"
Requires-Dist: sympy; extra == "dev"
